m3da/__init__.py
m3da/tools.py
m3da-0.1.2.dist-info/METADATA
m3da-0.1.2.dist-info/WHEEL
m3da-0.1.2.dist-info/top_level.txt
m3da-0.1.2.dist-info/RECORD
