Metadata-Version: 2.4
Name: m3da
Version: 0.1.2
Summary: A lightweight package for image classification using ONNX models
Home-page: https://github.com/GracePeterMutiibwa/m3da
Author: Mutiibwa Grace Peter
Author-email: androm3dalabs@gmail.com
Project-URL: Bug Tracker, https://github.com/GracePeterMutiibwa/m3da/issues
Keywords: onnx,machine learning,deep learning,image classification,ai
Classifier: Programming Language :: Python :: 3
Classifier: Programming Language :: Python :: 3.7
Classifier: Programming Language :: Python :: 3.8
Classifier: Programming Language :: Python :: 3.9
Classifier: Programming Language :: Python :: 3.10
Classifier: Operating System :: OS Independent
Classifier: Topic :: Scientific/Engineering :: Artificial Intelligence
Classifier: Topic :: Software Development :: Libraries :: Python Modules
Requires-Python: >=3.7
Requires-Dist: numpy>=1.19.0
Requires-Dist: onnxruntime>=1.7.0
Requires-Dist: Pillow>=8.0.0
Dynamic: author
Dynamic: author-email
Dynamic: classifier
Dynamic: description
Dynamic: description-content-type
Dynamic: home-page
Dynamic: keywords
Dynamic: project-url
Dynamic: requires-dist
Dynamic: requires-python
Dynamic: summary
